stock/__init__.py
stock/bin.py
stock/core.py
stock/version.json
stock_quote_client-1.0.2.dist-info/METADATA
stock_quote_client-1.0.2.dist-info/WHEEL
stock_quote_client-1.0.2.dist-info/entry_points.txt
stock_quote_client-1.0.2.dist-info/top_level.txt
stock_quote_client-1.0.2.dist-info/RECORD
